[
  {
    "name_text": "Мариам А.",
    "url": "https://youdo.com/u3265837",
    "skills": "Здравствуйте! Профессиональный лингвист-педагог со стажем 7 лет педагогической работы с детьми и взрослыми. Являюсь выпускником гуманитарно-прикладных наук МГЛУ (бывш.МГП…",
    "image": "https://avatar.youdo.com/get.userAvatar?AvatarId=6739835&AvatarType=H116W116"
  },
  {
    "name_text": "Яна К.",
    "url": "https://youdo.com/u4992861",
    "skills": "В связи с карантином закрывают вузы , прошу обратить внимание , что возвратов по работам нет , в случаях «передумал» или «не актуально» так как работа заказана и ведётся.…",
    "image": "https://avatar.youdo.com/get.userAvatar?AvatarId=7050526&AvatarType=H116W116"
  },
  {
    "name_text": "Виктор М.",
    "url": "https://youdo.com/u5291982",
    "skills": "Здравствуйте! Меня зовут Виктор, я являюсь сертифицированным (IELTS) преподавателем английского языка. После университета я уехал жить и работать в Лондон, где успешно п…",
    "image": "https://avatar.youdo.com/get.userAvatar?AvatarId=3344096&AvatarType=H116W116"
  },
  {
    "name_text": "Энрике Г.",
    "url": "https://youdo.com/u8141242",
    "skills": "Добро пожаловать на мой профиль! 👌Мои гарантии: 💯Работа выполняется в полном объёме. Я люблю работать «на отлично» с первого раза, поэтому всё записываю и ничего не з…",
    "image": "https://avatar.youdo.com/get.userAvatar?AvatarId=5976487&AvatarType=H116W116"
  },
  {
    "name_text": "Даниэль М.",
    "url": "https://youdo.com/u6204488",
    "skills": "Hi everyone, my name is Daniel Molgan and I am a native speaker of English working in Moscow. I am a linguist as well as an English as a Foreign Language (EFL) practition…",
    "image": "https://avatar.youdo.com/get.userAvatar?AvatarId=5328853&AvatarType=H116W116"
  },
  {
    "name_text": "Виктория З.",
    "url": "https://youdo.com/u8800807",
    "skills": "Меня зовут Вика и у меня огромный опыт работы во фрилансе. Работаю по многим направлениям. Проходила курсы по копирайтингу и рерайтингу. Также работаю менеджером по рекл…",
    "image": "https://avatar.youdo.com/get.userAvatar?AvatarId=6600221&AvatarType=H116W116"
  },
  {
    "name_text": "Ирина Г.",
    "url": "https://youdo.com/u6934531",
    "skills": "",
    "image": "https://avatar.youdo.com/get.userAvatar?AvatarId=4829269&AvatarType=H116W116"
  },
  {
    "name_text": "Екатерина Я.",
    "url": "https://youdo.com/u9037873",
    "skills": "Я преподаватель английского. Преподаю ОНЛАЙН с 2015 года. Основа языка - это услышать и ответить. Все дети умеют это делать, и только в 5-6 лет они начинают учиться читат…",
    "image": "https://avatar.youdo.com/get.userAvatar?AvatarId=6838293&AvatarType=H116W116"
  },
  {
    "name_text": "Григорий Э.",
    "url": "https://youdo.com/u7694301",
    "skills": "Оказываю помощь в написании студенческих и школьных работ. Люблю свое дело, подхожу к нему ответственно и дисциплинированно. Гарантирую качество своей работы.",
    "image": "https://avatar.youdo.com/get.userAvatar?AvatarId=5635096&AvatarType=H116W116"
  },
  {
    "name_text": "Елизавета С.",
    "url": "https://youdo.com/u6107054",
    "skills": "Добрый день! Меня зовут Лиза, я выпускница СПБГТИ(ТУ). Инженерно-технологический факультет. Я самый настоящий виртуальный помощник, потому что: Свободно владею английск…",
    "image": "https://avatar.youdo.com/get.userAvatar?AvatarId=5857595&AvatarType=H116W116"
  },
  {
    "name_text": "Сошала В.",
    "url": "https://youdo.com/u5290552",
    "skills": "Hello everyone! I am a student of Bauman Moscow state technical University studying mechatronics and robotics from Sri Lanka. Qualifications: - Passed the state exams of…",
    "image": "https://avatar.youdo.com/get.userAvatar?AvatarId=6580658&AvatarType=H116W116"
  },
  {
    "name_text": "Михаил О.",
    "url": "https://youdo.com/u1845018",
    "skills": "Я математик по образованию, в 2004 году получил MBA в Мanchester Business School. Свободно владею английским, грамотный русский (да, и у математиков такое может быть :)).…",
    "image": "https://avatar.youdo.com/get.userAvatar?AvatarId=6018090&AvatarType=H116W116"
  },
  {
    "name_text": "Алла К.",
    "url": "https://youdo.com/u8972405",
    "skills": "Более 25 лет работаю репетитором по английскому языку. За это время я помогла многим ученикам повысить уровень английского языка, начать “говорить”, успешно сдать ЕГЭ и …",
    "image": "https://avatar.youdo.com/get.userAvatar?AvatarId=6776735&AvatarType=H116W116"
  },
  {
    "name_text": "Майя М.",
    "url": "https://youdo.com/u1410507",
    "skills": "Являюсь профессиональным переводчиком и преподавателем. Английский, итальянский, грузинский – письменный и устный – продвинутый уровень, отличное знание специфики перевод…",
    "image": "https://avatar.youdo.com/get.userAvatar?AvatarId=4665290&AvatarType=H116W116"
  },
  {
    "name_text": "Вероника Б.",
    "url": "https://youdo.com/u8887135",
    "skills": "Преподаватель английского в университете более 20 лет, кандидат педагогических наук (2005), доцент (2007), более 10 лет руководила языковыми кафедрами, международные серт…",
    "image": "https://avatar.youdo.com/get.userAvatar?AvatarId=6693529&AvatarType=H116W116"
  },
  {
    "name_text": "Илья А.",
    "url": "https://youdo.com/u4845354",
    "skills": "Здравствуйте, уважаемые клиенты. Коротко о своих навыках: Английский язык: Изучаю с первого класса английской школы. Более года посвящал не менее 6 часов своего времени …",
    "image": "https://avatar.youdo.com/get.userAvatar?AvatarId=3304864&AvatarType=H116W116"
  },
  {
    "name_text": "Эмма Б.",
    "url": "https://youdo.com/u4892677",
    "skills": "Учитель с высшим лингвистическим (англ., фр. яз) и педагогическим образованиями, опыт работы 18 лет, подготовка к ЕГЭ и ОГЭ, получение сертификатов CAMBRIDGE , OXFORD, ра…",
    "image": "https://avatar.youdo.com/get.userAvatar?AvatarId=3228421&AvatarType=H116W116"
  },
  {
    "name_text": "Валерия М.",
    "url": "https://youdo.com/u9010284",
    "skills": "Всем добрый день! Меня зовут Валерия. Мне 32. 🔹Пpедлaгaю пpофeссиональную помoщь в изучении aнглийскoгo языка. ➡️Нa cвoиx зaнятиях применяю pазличныe метoдики в зaвиси…",
    "image": "https://avatar.youdo.com/get.userAvatar?AvatarId=6812569&AvatarType=H116W116"
  },
  {
    "name_text": "Минас М.",
    "url": "https://youdo.com/u9105889",
    "skills": "Окончил Финансовый университет. Работаю по специальности в банке. Готов Вам помочь по следующим категориям: - решение финансовых и экономических задач разного характера …",
    "image": "https://avatar.youdo.com/get.userAvatar?AvatarId=6900484&AvatarType=H116W116"
  },
  {
    "name_text": "Дарьяна З.",
    "url": "https://youdo.com/u7711147",
    "skills": "Выполняю ответственно и качественно заказы в максимально короткие сроки, возможно срочное выполнение за 2-3 часа с момента заказа. АНГЛИЙСКИЙ ЯЗЫК - Знание английского я…",
    "image": "https://avatar.youdo.com/get.userAvatar?AvatarId=5497822&AvatarType=H116W116"
  },
  {
    "name_text": "Диля К.",
    "url": "https://youdo.com/u1812335",
    "skills": "Добрый день! Предлагаю свои услуги в качестве репетитора английского языка🇬🇧 Обучение с нуля до продвинутого уровня 🇺🇸 Индивидуальные и групповые занятия👭 Подготовка…",
    "image": "https://avatar.youdo.com/get.userAvatar?AvatarId=5175204&AvatarType=H116W116"
  },
  {
    "name_text": "Татьяна Ц.",
    "url": "https://youdo.com/u8917734",
    "skills": "Здравствуйте, меня зовут Татьяна Николаевна. Первое высшее образование экономический факультет в СПбГУ. Второе высшее образование юриспруденция СПбГУ. Готова выполнить к…",
    "image": "https://avatar.youdo.com/get.userAvatar?AvatarId=6724577&AvatarType=H116W116"
  },
  {
    "name_text": "Анна С.",
    "url": "https://youdo.com/u7234819",
    "skills": "Обучаю английскому, итальянскому и японскому языкам. Имею высшее педагогическое образование. Стажировалась в языковых школах Италии и Японии. Преподаю 12 лет. Только …",
    "image": "https://avatar.youdo.com/get.userAvatar?AvatarId=5090879&AvatarType=H116W116"
  },
  {
    "name_text": "Тихон П.",
    "url": "https://youdo.com/u1488982",
    "skills": "Студент СПБГУ Репетитор по математике и информатике-школьная,вузовская программы,подготовка к ОГЭ и ЕГЭ. Имеется опыт работы. Результаты смотрите на фото. Репетитор по а…",
    "image": "https://avatar.youdo.com/get.userAvatar?AvatarId=2498884&AvatarType=H116W116"
  },
  {
    "name_text": "Татьяна М.",
    "url": "https://youdo.com/u8759873",
    "skills": "Опыт работы преподавателем с 2012 года. Много путешествовала по миру и жила в разных странах. Сертификат DELF, TESOL. Добрый день. Меня зовут Татьяна. Я преподаватель…",
    "image": "https://avatar.youdo.com/get.userAvatar?AvatarId=6558369&AvatarType=H116W116"
  },
  {
    "name_text": "Анна Т.",
    "url": "https://youdo.com/u3545490",
    "skills": "Здравствуйте! Меня зовут Анна 😊 Я являюсь репетитором по английскому и русскому языкам. Репетиторский стаж: 3 года. Провожу уроки по Skype, WhatsApp. На данный момент я…",
    "image": "https://avatar.youdo.com/get.userAvatar?AvatarId=6807505&AvatarType=H116W116"
  },
  {
    "name_text": "Татьяна О.",
    "url": "https://youdo.com/u8584464",
    "skills": "Преподаватель Английского и Китайского языка. Занятия проводятся удаленно, через Skype или Zoom Каждому моему ученику подбирается индивидуальная программа, учитываются е…",
    "image": "https://avatar.youdo.com/get.userAvatar?AvatarId=6357995&AvatarType=H116W116"
  },
  {
    "name_text": "Полина Ш.",
    "url": "https://youdo.com/u6789699",
    "skills": "Преподаватель, влюбленная в английский. Готова делиться своими знаниями!",
    "image": "https://avatar.youdo.com/get.userAvatar?AvatarId=4694375&AvatarType=H116W116"
  },
  {
    "name_text": "Татьяна И.",
    "url": "https://youdo.com/u8829083",
    "skills": "Образование: бакалавриат - РГПУ им. А.И. Герцена, Санкт-Петербург, магистратура - Сорбонна 4, Париж, Франция. Языки: - английский - французский Виды работ: - Веду у…",
    "image": "https://avatar.youdo.com/get.userAvatar?AvatarId=6969607&AvatarType=H116W116"
  },
  {
    "name_text": "Юлия Б.",
    "url": "https://youdo.com/u9060430",
    "skills": "Добрый день! Спасибо, что выбрали мои услуги, я лингвист-международник и предлагаю различный спектр услуг от написания текстов до перевода документов. С подробной информа…",
    "image": "https://avatar.youdo.com/get.userAvatar?AvatarId=6859017&AvatarType=H116W116"
  },
  {
    "name_text": "Екатерина О.",
    "url": "https://youdo.com/u9043731",
    "skills": "Преподаю английский взрослым и детям. Грамматика, разговорный курс. Работала преподавателем английского в Бразилии, Китае, Тайланде. Училась на английском в Дании. Готови…",
    "image": "https://avatar.youdo.com/get.userAvatar?AvatarId=6918977&AvatarType=H116W116"
  },
  {
    "name_text": "Владислав Ф.",
    "url": "https://youdo.com/u7739452",
    "skills": "Привет, я Владислав, факультет Вычислительной Математики и Кибернетики МГУ имени М.В. Ломоносова. Являюсь победителем всероссийских математических и физических олимпи…",
    "image": "https://avatar.youdo.com/get.userAvatar?AvatarId=6964011&AvatarType=H116W116"
  },
  {
    "name_text": "Елена А.",
    "url": "https://youdo.com/u6315731",
    "skills": "Преподаватель английского языка, кандидат филологических наук, стаж: более 20 лет. Специалист по грамматике и фонетике английского языка. Работаю в ВУЗе. Полиглот, знаю б…",
    "image": "https://avatar.youdo.com/get.userAvatar?AvatarId=4298004&AvatarType=H116W116"
  },
  {
    "name_text": "Тимур Г.",
    "url": "https://youdo.com/u8300885",
    "skills": "Имею два высших образования. Окончил СПБГУ факультеты Юриспруденция и Международные отношения. До этого учился несколько лет в США, так что у меня свободный английский. Р…",
    "image": "https://avatar.youdo.com/get.userAvatar?AvatarId=6644002&AvatarType=H116W116"
  },
  {
    "name_text": "Виктория Р.",
    "url": "https://youdo.com/u9116633",
    "skills": "Переводчик Английский-Русский. Есть опыт переводов. Профильное образование. Есть сертификат TOEFL.",
    "image": "https://avatar.youdo.com/get.userAvatar?AvatarId=6909428&AvatarType=H116W116"
  },
  {
    "name_text": "Елизавета К.",
    "url": "https://youdo.com/u5868716",
    "skills": "Добрый день! Меня зовут Елизавета. Я преподаватель иностранных языков (немецкий/ английский). Образование: Высшее. Окончила Московский Педагогический Государственный Ун…",
    "image": "https://avatar.youdo.com/get.userAvatar?AvatarId=6059590&AvatarType=H116W116"
  },
  {
    "name_text": "Юлия Б.",
    "url": "https://youdo.com/u7118269",
    "skills": "Здравствуй, заказчик! Меня зовут Юлия, я учитель английского и немецкого языков. Уровень владения языками:С2. Имею 2 высших образования: ВГСПУ и Ранхигс (экономист). …",
    "image": "https://avatar.youdo.com/get.userAvatar?AvatarId=4993628&AvatarType=H116W116"
  },
  {
    "name_text": "Диана К.",
    "url": "https://youdo.com/u4085014",
    "skills": "Добрый день! Предлагаю обучение английскому языку - как разговорному, так и по университетскими программам (TOEFL, IELTS). Базовая методика Cambridge University. Анг…",
    "image": "https://avatar.youdo.com/get.userAvatar?AvatarId=6737885&AvatarType=H116W116"
  },
  {
    "name_text": "Екатерина А.",
    "url": "https://youdo.com/u7202559",
    "skills": "Юрист-международник со знанием трёх иностранных языков, большим опытом написания дипломных и курсовых работ, а также преподавания.",
    "image": "https://avatar.youdo.com/get.userAvatar?AvatarId=5063939&AvatarType=H116W116"
  },
  {
    "name_text": "Алена Г.",
    "url": "https://youdo.com/u3692176",
    "skills": "Образование: Пермский государственный технический университет с, факультет гуманитарных наук, специальность – перевод и переводоведение (2013 г.). Синхронный переводчик …",
    "image": "https://avatar.youdo.com/get.userAvatar?AvatarId=6084733&AvatarType=H116W116"
  },
  {
    "name_text": "Анна Н.",
    "url": "https://youdo.com/u3692021",
    "skills": "Профессиональный репетитор английского языка с многолетним стажем, в том числе по скайпу. Подробности о предлагаемых программах и отзывы можно почитать в альбоме в много…",
    "image": "https://avatar.youdo.com/get.userAvatar?AvatarId=2595884&AvatarType=H116W116"
  },
  {
    "name_text": "Дарья П.",
    "url": "https://youdo.com/u4903749",
    "skills": "Добрый день! Меня зовут Дарья. Я являюсь переводчиком и преподавателем английского языка более 6 лет. Последнии 7 лет работала и училась в Америке и Италии, говорю на «…",
    "image": "https://avatar.youdo.com/get.userAvatar?AvatarId=3167693&AvatarType=H116W116"
  },
  {
    "name_text": "Олег З.",
    "url": "https://youdo.com/u6065832",
    "skills": "Добро пожаловать 😇 Вся грамматика будет понятна за 3-15 занятий. Далее, подсматривая в 4 таблички, все доводится до автоматизма 🔝🇬🇧😇 Приглашаю быстро и без лишних …",
    "image": "https://avatar.youdo.com/get.userAvatar?AvatarId=4043056&AvatarType=H116W116"
  },
  {
    "name_text": "Михаил В.",
    "url": "https://youdo.com/u8653088",
    "skills": "Профессиональный психолог и репетитор по английскому. Международный сертификат преподавателя английского как второго языка ( сертификат с отличием). Как репетитор, занима…",
    "image": "https://avatar.youdo.com/get.userAvatar?AvatarId=6552039&AvatarType=H116W116"
  },
  {
    "name_text": "Дина С.",
    "url": "https://youdo.com/u8665315",
    "skills": "Добрый день! Я Дина, очень приятно. Первое образование - в сфере программирования, второе - экономическое. Свободно владею английским языком. С удовольствием помогу вам …",
    "image": "https://avatar.youdo.com/get.userAvatar?AvatarId=6769664&AvatarType=H116W116"
  },
  {
    "name_text": "Анастасия Т.",
    "url": "https://youdo.com/u8826365",
    "skills": "Опыт работы и достижения: - Успешная сдача ЕГЭ по английскому языку (2019) на 98 баллов. - Успешная сдача международного экзамена PTE (2018) и получение сертификата, под…",
    "image": "https://avatar.youdo.com/get.userAvatar?AvatarId=6680364&AvatarType=H116W116"
  },
  {
    "name_text": "Анастасия А.",
    "url": "https://youdo.com/u6337502",
    "skills": "Здравствуйте! Меня зовут Анастасия. Предлагаю вам свои услуги репетитора английского языка:) Я вам подхожу если: 1. Вы мечтаете начать изучать английский; 2. Вам недоста…",
    "image": "https://avatar.youdo.com/get.userAvatar?AvatarId=6573469&AvatarType=H116W116"
  },
  {
    "name_text": "Анна Р.",
    "url": "https://youdo.com/u9089690",
    "skills": "8 лет жила в Великобритании — свободно владею Английским языком :) Получила высшее образование в 2х университетах Англии. ИНДИВИДУАЛЬНЫЙ подход к каждому заданию, в соот…",
    "image": "https://avatar.youdo.com/get.userAvatar?AvatarId=6886224&AvatarType=H116W116"
  },
  {
    "name_text": "Марта С.",
    "url": "https://youdo.com/u1211418",
    "skills": "Предлагаю индивидуальные уроки в режиме online (скайп, what’s app, zoom) для детей и взрослых: общая программа, разговорный английский, подготовка к ОГЭ, ЕГЭ • 7 лет опыт…",
    "image": "https://avatar.youdo.com/get.userAvatar?AvatarId=6853985&AvatarType=H116W116"
  },
  {
    "name_text": "Лидия Г.",
    "url": "https://youdo.com/u8947070",
    "skills": "Здравствуйте! Я молодой, но опытный преподаватель. - У меня высшее педагогическое и психологиеское образование (3 красных диплома!) - Опыт работы - 6 лет, из них один го…",
    "image": "https://avatar.youdo.com/get.userAvatar?AvatarId=6758112&AvatarType=H116W116"
  }
]